{
  "schemaVersion": "eip.run-request.v1",
  "id": "req_01HV7Y8M8F2KQ5W3P9R6T4N2DA",
  "correlationId": "corr_01HV7Y8M8F2KQ5W3P9R6T4N2DB",
  "idempotencyKey": "manual-request-20260429-2",
  "source": {
    "sourceId": "source_01HV7Y8M8F2KQ5W3P9R6T4N2DC",
    "sourceType": "manual"
  },
  "requestedBy": {
    "actorId": "actor_01HV7Y8M8F2KQ5W3P9R6T4N2DD",
    "actorType": "human"
  },
  "workItem": {
    "workItemId": "workitem_01HV7Y8M8F2KQ5W3P9R6T4N2DE",
    "externalId": "manual-secret-check"
  },
  "mode": "validate",
  "createdAt": "2026-04-29T02:00:00Z",
  "extensions": {
    "x-raw-secret": "REDACTED_FIXTURE_SECRET_PLACEHOLDER"
  }
}
