{
  "schemaVersion": "eip.run-request.v1",
  "id": "req_01HV7Y8M8F2KQ5W3P9R6T4N2FA",
  "correlationId": "corr_01HV7Y8M8F2KQ5W3P9R6T4N2FB",
  "idempotencyKey": "github-issue-4-attempt-1",
  "source": {
    "sourceId": "source_01HV7Y8M8F2KQ5W3P9R6T4N2FC",
    "sourceType": "github"
  },
  "requestedBy": {
    "actorId": "actor_01HV7Y8M8F2KQ5W3P9R6T4N2FD",
    "actorType": "api_client"
  },
  "workItem": {
    "workItemId": "workitem_01HV7Y8M8F2KQ5W3P9R6T4N2FE",
    "externalId": "4"
  },
  "mode": "plan",
  "createdAt": "2026-04-29T01:45:45Z",
  "transport": "github-webhook"
}
